{
  "$schema": "https://developer.microsoft.com/json-schemas/fabric/item/report/definition/visualContainer/2.4.0/schema.json",
  "name": "0fb92ddb66217e77379b",
  "position": {
    "x": 31.260083344545063,
    "y": 157.67348974360118,
    "z": 5625,
    "height": 251.66666666666669,
    "width": 351.66666666666669,
    "tabOrder": 12009
  },
  "visual": {
    "visualType": "textbox",
    "objects": {
      "general": [
        {
          "properties": {
            "paragraphs": [
              {
                "textRuns": [
                  {
                    "value": "Across all major carriers, there is a consistent disparity between promised delivery windows and actual performance. "
                  },
                  {
                    "value": "FedEx",
                    "textStyle": {
                      "fontWeight": "bold"
                    }
                  },
                  {
                    "value": " exhibits the largest gap, with an actual lead time of "
                  },
                  {
                    "value": "4.4 days",
                    "textStyle": {
                      "fontWeight": "bold"
                    }
                  },
                  {
                    "value": " against a promised "
                  },
                  {
                    "value": "3.0 days",
                    "textStyle": {
                      "fontWeight": "bold"
                    }
                  },
                  {
                    "value": ". While "
                  },
                  {
                    "value": "UPS",
                    "textStyle": {
                      "fontWeight": "bold"
                    }
                  },
                  {
                    "value": " maintains the shortest actual lead time at "
                  },
                  {
                    "value": "3.8 days",
                    "textStyle": {
                      "fontWeight": "bold"
                    }
                  },
                  {
                    "value": ", it still fails to meet its "
                  },
                  {
                    "value": "2.8-day",
                    "textStyle": {
                      "fontWeight": "bold"
                    }
                  },
                  {
                    "value": " promise. Overall, the data indicates a systemic underestimation of lead times, as every carrier exceeds their promised delivery window by at least one full day."
                  }
                ]
              }
            ]
          }
        }
      ]
    },
    "visualContainerObjects": {
      "background": [
        {
          "properties": {
            "show": {
              "expr": {
                "Literal": {
                  "Value": "true"
                }
              }
            }
          }
        }
      ],
      "padding": [
        {
          "properties": {
            "top": {
              "expr": {
                "Literal": {
                  "Value": "20D"
                }
              }
            },
            "bottom": {
              "expr": {
                "Literal": {
                  "Value": "20D"
                }
              }
            },
            "right": {
              "expr": {
                "Literal": {
                  "Value": "20D"
                }
              }
            },
            "left": {
              "expr": {
                "Literal": {
                  "Value": "20D"
                }
              }
            }
          }
        }
      ],
      "title": [
        {
          "properties": {
            "text": {
              "expr": {
                "Literal": {
                  "Value": "'info_text'"
                }
              }
            }
          }
        }
      ]
    },
    "drillFilterOtherVisuals": true
  },
  "parentGroupName": "03a0a12b051754709ab2",
  "isHidden": true
}